neroimpacket/Dot11Crypto.py
neroimpacket/Dot11KeyManager.py
neroimpacket/ICMP6.py
neroimpacket/IP6.py
neroimpacket/IP6_Address.py
neroimpacket/IP6_Extension_Headers.py
neroimpacket/ImpactDecoder.py
neroimpacket/ImpactPacket.py
neroimpacket/NDP.py
neroimpacket/__init__.py
neroimpacket/cdp.py
neroimpacket/crypto.py
neroimpacket/dhcp.py
neroimpacket/dns.py
neroimpacket/dot11.py
neroimpacket/dpapi.py
neroimpacket/eap.py
neroimpacket/ese.py
neroimpacket/helper.py
neroimpacket/hresult_errors.py
neroimpacket/http.py
neroimpacket/mapi_constants.py
neroimpacket/mqtt.py
neroimpacket/nmb.py
neroimpacket/nt_errors.py
neroimpacket/ntlm.py
neroimpacket/pcap_linktypes.py
neroimpacket/pcapfile.py
neroimpacket/smb.py
neroimpacket/smb3.py
neroimpacket/smb3structs.py
neroimpacket/smbconnection.py
neroimpacket/smbserver.py
neroimpacket/spnego.py
neroimpacket/structure.py
neroimpacket/system_errors.py
neroimpacket/tds.py
neroimpacket/uuid.py
neroimpacket/version.py
neroimpacket/winregistry.py
neroimpacket/wps.py
neroimpacket/dcerpc/__init__.py
neroimpacket/dcerpc/v5/__init__.py
neroimpacket/dcerpc/v5/atsvc.py
neroimpacket/dcerpc/v5/bkrp.py
neroimpacket/dcerpc/v5/dcomrt.py
neroimpacket/dcerpc/v5/dhcpm.py
neroimpacket/dcerpc/v5/drsuapi.py
neroimpacket/dcerpc/v5/dssp.py
neroimpacket/dcerpc/v5/dtypes.py
neroimpacket/dcerpc/v5/enum.py
neroimpacket/dcerpc/v5/epm.py
neroimpacket/dcerpc/v5/even.py
neroimpacket/dcerpc/v5/even6.py
neroimpacket/dcerpc/v5/iphlp.py
neroimpacket/dcerpc/v5/lsad.py
neroimpacket/dcerpc/v5/lsat.py
neroimpacket/dcerpc/v5/mgmt.py
neroimpacket/dcerpc/v5/mimilib.py
neroimpacket/dcerpc/v5/ndr.py
neroimpacket/dcerpc/v5/nrpc.py
neroimpacket/dcerpc/v5/nspi.py
neroimpacket/dcerpc/v5/oxabref.py
neroimpacket/dcerpc/v5/par.py
neroimpacket/dcerpc/v5/rpch.py
neroimpacket/dcerpc/v5/rpcrt.py
neroimpacket/dcerpc/v5/rprn.py
neroimpacket/dcerpc/v5/rrp.py
neroimpacket/dcerpc/v5/samr.py
neroimpacket/dcerpc/v5/sasec.py
neroimpacket/dcerpc/v5/scmr.py
neroimpacket/dcerpc/v5/srvs.py
neroimpacket-0.12.0.dist-info/LICENSE
neroimpacket-0.12.0.dist-info/METADATA
neroimpacket-0.12.0.dist-info/WHEEL
neroimpacket-0.12.0.dist-info/top_level.txt
neroimpacket-0.12.0.dist-info/RECORD
